README.rst
setup.cfg
setup.py
versioneer.py
bin/mouse-picture
bin/mouse-preview
bin/mouse-record
mouse/__init__.py
mouse/_version.py
mouse/picture.py
mouse/preview.py
mouse/record.py
mouse_record.egg-info/PKG-INFO
mouse_record.egg-info/SOURCES.txt
mouse_record.egg-info/dependency_links.txt
mouse_record.egg-info/pbr.json
mouse_record.egg-info/requires.txt
mouse_record.egg-info/top_level.txt
mouse_record.egg-info/zip-safe