Metadata-Version: 1.0
Name: mouse-record
Version: 0.0.6
Summary: An Event Triggered Recorder
Home-page: https://github.com/DudLab/mouse_record
Author: Bailey Hwa
Author-email: hwab@janelia.hhmi.org
License: GPLv3
Platform: UNKNOWN
